janzeng/__init__.py
janzeng/entity.py
janzeng/event.py
janzeng/game.py
janzeng/keys.py
janzeng/sprite.py
janzeng/utils.py
janzeng-0.0.1.dev1.dist-info/LICENSE
janzeng-0.0.1.dev1.dist-info/WHEEL
janzeng-0.0.1.dev1.dist-info/METADATA
janzeng-0.0.1.dev1.dist-info/RECORD
