Metadata-Version: 2.1
Name: janzeng
Version: 0.0.1.dev1
Summary: Game engine for Pygame
Home-page: https://github.com/jtiai/janzeng
License: BSD-3-Clause
Author: Jani Tiainen
Author-email: jani@tiainen.cc
Requires-Python: >=3.7,<4.0
Classifier: License :: OSI Approved :: BSD License
Classifier: Programming Language :: Python :: 3
Classifier: Programming Language :: Python :: 3.7
Classifier: Programming Language :: Python :: 3.8
Classifier: Programming Language :: Python :: 3.9
Classifier: Topic :: Software Development :: Libraries :: pygame
Requires-Dist: importlib-metadata (>=1.0,<2.0); python_version < "3.8"
Requires-Dist: pygame (>=2.0.0,<3.0.0)
Project-URL: Bug Tracker, https://github.com/jtiai/pygame-colliders/issues
Project-URL: Documentation, https://pygamejanzeng.readthedocs.io/
Project-URL: Repository, https://github.com/jtiai/janzeng
